{"box_data": [{"position": {"minX": 408.60400390625, "minY": 168.0533447265625, "maxX": 496.83074951171875, "maxY": 200.59616088867188}, "class_id": 4, "box_caption": "airplane 0.861", "scores": {"class_score": 0.8605355620384216}, "domain": "pixel"}, {"position": {"minX": 418.0301818847656, "minY": 179.30296325683594, "maxX": 484.9326477050781, "maxY": 199.60740661621094}, "class_id": 4, "box_caption": "airplane 0.010", "scores": {"class_score": 0.010216599330306053}, "domain": "pixel"}, {"position": {"minX": 408.75372314453125, "minY": 168.5169677734375, "maxX": 498.0755615234375, "maxY": 200.7183837890625}, "class_id": 7, "box_caption": "truck 0.006", "scores": {"class_score": 0.006139092613011599}, "domain": "pixel"}, {"position": {"minX": 411.90155029296875, "minY": 174.74530029296875, "maxX": 468.04656982421875, "maxY": 197.02096557617188}, "class_id": 4, "box_caption": "airplane 0.003", "scores": {"class_score": 0.0028601090889424086}, "domain": "pixel"}, {"position": {"minX": 421.4244079589844, "minY": 171.710693359375, "maxX": 483.0216979980469, "maxY": 197.08407592773438}, "class_id": 4, "box_caption": "airplane 0.003", "scores": {"class_score": 0.0026050477754324675}, "domain": "pixel"}, {"position": {"minX": 409.7232360839844, "minY": 168.1725311279297, "maxX": 495.5623474121094, "maxY": 200.35536193847656}, "class_id": 8, "box_caption": "boat 0.002", "scores": {"class_score": 0.002310969401150942}, "domain": "pixel"}, {"position": {"minX": 408.75372314453125, "minY": 168.5169677734375, "maxX": 498.0755615234375, "maxY": 200.7183837890625}, "class_id": 2, "box_caption": "car 0.002", "scores": {"class_score": 0.002280128188431263}, "domain": "pixel"}, {"position": {"minX": 408.75372314453125, "minY": 168.5169677734375, "maxX": 498.0755615234375, "maxY": 200.7183837890625}, "class_id": 5, "box_caption": "bus 0.002", "scores": {"class_score": 0.0019262753194198012}, "domain": "pixel"}, {"position": {"minX": 295.23553466796875, "minY": 197.8166046142578, "maxX": 301.36004638671875, "maxY": 204.58631896972656}, "class_id": 8, "box_caption": "boat 0.002", "scores": {"class_score": 0.0017381910001859069}, "domain": "pixel"}, {"position": {"minX": 412.5908203125, "minY": 179.35806274414062, "maxX": 451.36480712890625, "maxY": 196.48370361328125}, "class_id": 4, "box_caption": "airplane 0.002", "scores": {"class_score": 0.0017298440216109157}, "domain": "pixel"}, {"position": {"minX": 408.33837890625, "minY": 153.189697265625, "maxX": 501.2452392578125, "maxY": 206.20498657226562}, "class_id": 4, "box_caption": "airplane 0.001", "scores": {"class_score": 0.0014958587707951665}, "domain": "pixel"}, {"position": {"minX": 410.8304748535156, "minY": 179.46054077148438, "maxX": 437.5699157714844, "maxY": 193.16329956054688}, "class_id": 4, "box_caption": "airplane 0.001", "scores": {"class_score": 0.0013921399367973208}, "domain": "pixel"}, {"position": {"minX": 295.23553466796875, "minY": 197.8166046142578, "maxX": 301.36004638671875, "maxY": 204.58631896972656}, "class_id": 2, "box_caption": "car 0.001", "scores": {"class_score": 0.0013529033167287707}, "domain": "pixel"}, {"position": {"minX": 436.1522521972656, "minY": 173.94964599609375, "maxX": 467.0143127441406, "maxY": 195.42837524414062}, "class_id": 4, "box_caption": "airplane 0.001", "scores": {"class_score": 0.001229412155225873}, "domain": "pixel"}, {"position": {"minX": 408.9635009765625, "minY": 168.75747680664062, "maxX": 497.43585205078125, "maxY": 200.35208129882812}, "class_id": 71, "box_caption": "sink 0.001", "scores": {"class_score": 0.0011476005893200636}, "domain": "pixel"}, {"position": {"minX": 415.970947265625, "minY": 184.8660430908203, "maxX": 456.27392578125, "maxY": 196.55165100097656}, "class_id": 4, "box_caption": "airplane 0.001", "scores": {"class_score": 0.0011242561740800738}, "domain": "pixel"}, {"position": {"minX": 408.9635009765625, "minY": 168.75747680664062, "maxX": 497.43585205078125, "maxY": 200.35208129882812}, "class_id": 6, "box_caption": "train 0.001", "scores": {"class_score": 0.0010583024704828858}, "domain": "pixel"}, {"position": {"minX": 409.7232360839844, "minY": 168.1725311279297, "maxX": 495.5623474121094, "maxY": 200.35536193847656}, "class_id": 33, "box_caption": "kite 0.001", "scores": {"class_score": 0.0010528574930503964}, "domain": "pixel"}], "class_labels": {"0": "person", "1": "bicycle", "2": "car", "3": "motorcycle", "4": "airplane", "5": "bus", "6": "train", "7": "truck", "8": "boat", "9": "traffic light", "10": "fire hydrant", "11": "stop sign", "12": "parking meter", "13": "bench", "14": "bird", "15": "cat", "16": "dog", "17": "horse", "18": "sheep", "19": "cow", "20": "elephant", "21": "bear", "22": "zebra", "23": "giraffe", "24": "backpack", "25": "umbrella", "26": "handbag", "27": "tie", "28": "suitcase", "29": "frisbee", "30": "skis", "31": "snowboard", "32": "sports ball", "33": "kite", "34": "baseball bat", "35": "baseball glove", "36": "skateboard", "37": "surfboard", "38": "tennis racket", "39": "bottle", "40": "wine glass", "41": "cup", "42": "fork", "43": "knife", "44": "spoon", "45": "bowl", "46": "banana", "47": "apple", "48": "sandwich", "49": "orange", "50": "broccoli", "51": "carrot", "52": "hot dog", "53": "pizza", "54": "donut", "55": "cake", "56": "chair", "57": "couch", "58": "potted plant", "59": "bed", "60": "dining table", "61": "toilet", "62": "tv", "63": "laptop", "64": "mouse", "65": "remote", "66": "keyboard", "67": "cell phone", "68": "microwave", "69": "oven", "70": "toaster", "71": "sink", "72": "refrigerator", "73": "book", "74": "clock", "75": "vase", "76": "scissors", "77": "teddy bear", "78": "hair drier", "79": "toothbrush"}}